{
  "clubs": [
    {
      "id": 1,
      "name": "クラブ・ぶん助",
      "color": "#4a7a35",
      "emblem_file": "emblem_bunsuke.png",
      "formation": "4-3-3",
      "is_player_club": true,
      "players": [
        {
          "id": 1,
          "name": "ぶん助",
          "full_name": "ぶん助・ザ・グレート",
          "position": "ST",
          "breed": "shiba",
          "age": 24,
          "shirt_number": 9,
          "image_file": "player_1.png",
          "physical":  {"speed": 88, "stamina": 82, "strength": 75, "agility": 85, "jumping": 80},
          "technical": {"dribbling": 85, "shooting": 92, "power": 90, "passing": 72, "crossing": 68, "heading": 78, "defending": 45, "tackling": 42, "gk_reflexes": 30, "gk_handling": 28},
          "mental":    {"soccer_iq": 80, "composure": 78, "leadership": 72, "aggression": 70, "dirtiness": 25, "bravery": 82, "teamwork": 75},
          "special_move_id": 1
        },
        {
          "id": 2,
          "name": "ブル",
          "full_name": "ブルドッグ・ブル",
          "position": "CF",
          "breed": "bulldog",
          "age": 28,
          "shirt_number": 10,
          "image_file": "player_2.png",
          "physical":  {"speed": 65, "stamina": 78, "strength": 92, "agility": 60, "jumping": 72},
          "technical": {"dribbling": 70, "shooting": 78, "power": 94, "passing": 65, "crossing": 60, "heading": 88, "defending": 55, "tackling": 52, "gk_reflexes": 30, "gk_handling": 28},
          "mental":    {"soccer_iq": 68, "composure": 62, "leadership": 65, "aggression": 85, "dirtiness": 40, "bravery": 90, "teamwork": 68},
          "special_move_id": 2
        },
        {
          "id": 3,
          "name": "キン太郎",
          "full_name": "キン太郎・ストーンウォール",
          "position": "CB",
          "breed": "saint_bernard",
          "age": 30,
          "shirt_number": 5,
          "image_file": "player_3.png",
          "physical":  {"speed": 55, "stamina": 85, "strength": 95, "agility": 52, "jumping": 88},
          "technical": {"dribbling": 45, "shooting": 40, "power": 72, "passing": 60, "crossing": 42, "heading": 90, "defending": 92, "tackling": 90, "gk_reflexes": 30, "gk_handling": 28},
          "mental":    {"soccer_iq": 75, "composure": 82, "leadership": 78, "aggression": 68, "dirtiness": 30, "bravery": 88, "teamwork": 80},
          "special_move_id": 3
        },
        {
          "id": 4,
          "name": "留二郎",
          "full_name": "老練・留二郎",
          "position": "CAM",
          "breed": "akita",
          "age": 38,
          "shirt_number": 8,
          "image_file": "player_4.png",
          "physical":  {"speed": 58, "stamina": 60, "strength": 62, "agility": 65, "jumping": 58},
          "technical": {"dribbling": 80, "shooting": 70, "power": 68, "passing": 92, "crossing": 85, "heading": 65, "defending": 60, "tackling": 58, "gk_reflexes": 30, "gk_handling": 28},
          "mental":    {"soccer_iq": 96, "composure": 92, "leadership": 90, "aggression": 50, "dirtiness": 10, "bravery": 75, "teamwork": 95},
          "special_move_id": 4
        },
        {
          "id": 5,
          "name": "菊次郎",
          "full_name": "疾風・菊次郎",
          "position": "RW",
          "breed": "border_collie",
          "age": 22,
          "shirt_number": 11,
          "image_file": "player_5.png",
          "physical":  {"speed": 96, "stamina": 88, "strength": 62, "agility": 94, "jumping": 72},
          "technical": {"dribbling": 90, "shooting": 72, "power": 68, "passing": 80, "crossing": 88, "heading": 62, "defending": 52, "tackling": 48, "gk_reflexes": 30, "gk_handling": 28},
          "mental":    {"soccer_iq": 88, "composure": 72, "leadership": 65, "aggression": 75, "dirtiness": 20, "bravery": 80, "teamwork": 78},
          "special_move_id": 5
        },
        {
          "id": 6,
          "name": "武",
          "full_name": "鉄壁・武",
          "position": "GK",
          "breed": "husky",
          "age": 27,
          "shirt_number": 1,
          "image_file": "player_6.png",
          "physical":  {"speed": 65, "stamina": 80, "strength": 78, "agility": 72, "jumping": 85},
          "technical": {"dribbling": 40, "shooting": 35, "power": 50, "passing": 62, "crossing": 40, "heading": 68, "defending": 70, "tackling": 65, "gk_reflexes": 92, "gk_handling": 90},
          "mental":    {"soccer_iq": 80, "composure": 88, "leadership": 75, "aggression": 60, "dirtiness": 15, "bravery": 95, "teamwork": 82},
          "special_move_id": 6
        },
        {
          "id": 7,
          "name": "セバスチャン",
          "full_name": "エレガント・セバスチャン",
          "position": "CM",
          "breed": "poodle",
          "age": 26,
          "shirt_number": 7,
          "image_file": "player_7.png",
          "physical":  {"speed": 75, "stamina": 82, "strength": 60, "agility": 82, "jumping": 65},
          "technical": {"dribbling": 88, "shooting": 75, "power": 70, "passing": 90, "crossing": 82, "heading": 62, "defending": 68, "tackling": 65, "gk_reflexes": 30, "gk_handling": 28},
          "mental":    {"soccer_iq": 90, "composure": 85, "leadership": 72, "aggression": 55, "dirtiness": 15, "bravery": 70, "teamwork": 88},
          "special_move_id": 7
        },
        {
          "id": 8,
          "name": "田中",
          "full_name": "ブルドッグ・田中",
          "position": "CDM",
          "breed": "bulldog",
          "age": 29,
          "shirt_number": 6,
          "image_file": "player_8.png",
          "physical":  {"speed": 62, "stamina": 88, "strength": 90, "agility": 58, "jumping": 75},
          "technical": {"dribbling": 58, "shooting": 55, "power": 80, "passing": 68, "crossing": 55, "heading": 78, "defending": 88, "tackling": 92, "gk_reflexes": 30, "gk_handling": 28},
          "mental":    {"soccer_iq": 72, "composure": 70, "leadership": 68, "aggression": 88, "dirtiness": 50, "bravery": 85, "teamwork": 75},
          "special_move_id": 8
        },
        {
          "id": 9,
          "name": "鼻男",
          "full_name": "嗅覚王・鼻男",
          "position": "CB",
          "breed": "beagle",
          "age": 25,
          "shirt_number": 4,
          "image_file": "player_9.png",
          "physical":  {"speed": 70, "stamina": 80, "strength": 75, "agility": 72, "jumping": 70},
          "technical": {"dribbling": 60, "shooting": 52, "power": 65, "passing": 70, "crossing": 58, "heading": 75, "defending": 85, "tackling": 82, "gk_reflexes": 30, "gk_handling": 28},
          "mental":    {"soccer_iq": 82, "composure": 75, "leadership": 62, "aggression": 65, "dirtiness": 28, "bravery": 78, "teamwork": 80},
          "special_move_id": 9
        },
        {
          "id": 10,
          "name": "餡兵衛",
          "full_name": "変幻自在・餡兵衛",
          "position": "LW",
          "breed": "dachshund",
          "age": 23,
          "shirt_number": 21,
          "image_file": "player_10.png",
          "physical":  {"speed": 90, "stamina": 75, "strength": 50, "agility": 92, "jumping": 58},
          "technical": {"dribbling": 92, "shooting": 68, "power": 62, "passing": 75, "crossing": 80, "heading": 50, "defending": 45, "tackling": 42, "gk_reflexes": 30, "gk_handling": 28},
          "mental":    {"soccer_iq": 78, "composure": 68, "leadership": 55, "aggression": 72, "dirtiness": 22, "bravery": 75, "teamwork": 72},
          "special_move_id": 10
        },
        {
          "id": 11,
          "name": "ガストン",
          "full_name": "欧州貴族・ガストン",
          "position": "LB",
          "breed": "golden",
          "age": 27,
          "shirt_number": 3,
          "image_file": "player_11.png",
          "physical":  {"speed": 80, "stamina": 85, "strength": 72, "agility": 78, "jumping": 75},
          "technical": {"dribbling": 78, "shooting": 72, "power": 75, "passing": 80, "crossing": 92, "heading": 68, "defending": 75, "tackling": 72, "gk_reflexes": 30, "gk_handling": 28},
          "mental":    {"soccer_iq": 80, "composure": 78, "leadership": 70, "aggression": 65, "dirtiness": 20, "bravery": 75, "teamwork": 82},
          "special_move_id": 11
        }
      ]
    }
  ],
  "special_moves": [
    {"id": 1,  "name": "流星ブルアタック",   "description": "青い炎を纏った必殺の一蹴！",           "image_file": "move_bunsuke.png",  "power": 95, "move_type": "SHOOT",   "cooldown": 5},
    {"id": 2,  "name": "ブル旋風脚",         "description": "竜巻のように回転して突破！",             "image_file": "move_buru.png",     "power": 75, "move_type": "DRIBBLE", "cooldown": 4},
    {"id": 3,  "name": "大岩守護壁",         "description": "岩のような体で全てを跳ね返す！",         "image_file": "move_kintaro.png",  "power": 80, "move_type": "TACKLE",  "cooldown": 4},
    {"id": 4,  "name": "老練の一閃",         "description": "80歳の経験が生む神業パス！",             "image_file": "move_tomejiro.png", "power": 70, "move_type": "SPIRIT",  "cooldown": 6},
    {"id": 5,  "name": "疾風縦突破",         "description": "サイドを切り裂く超高速ドリブル！",       "image_file": "move_kikujiro.png", "power": 72, "move_type": "DRIBBLE", "cooldown": 4},
    {"id": 6,  "name": "鋼鉄の前足",         "description": "GK武の鉄壁セーブ！",                   "image_file": "move_takeshi.png",  "power": 85, "move_type": "SAVE",    "cooldown": 5},
    {"id": 7,  "name": "エレガントビジョン", "description": "未来を見通す天才的司令塔プレー！",       "image_file": "move_sebastian.png","power": 78, "move_type": "DRIBBLE", "cooldown": 4},
    {"id": 8,  "name": "ブルドッグタックル", "description": "唸る体当たりで相手をなぎ倒す！",         "image_file": "move_tanaka.png",   "power": 82, "move_type": "TACKLE",  "cooldown": 4},
    {"id": 9,  "name": "嗅覚スキャン",       "description": "鼻でボールの軌道を完全予測！",           "image_file": "move_hanao.png",    "power": 74, "move_type": "TACKLE",  "cooldown": 4},
    {"id": 10, "name": "餡兵衛バウンド",     "description": "予測不能な変幻自在のドリブル！",         "image_file": "move_anbe.png",     "power": 71, "move_type": "DRIBBLE", "cooldown": 4},
    {"id": 11, "name": "欧州仕込みウィング", "description": "超速カットインからの豪快シュート！",     "image_file": "move_gaston.png",   "power": 80, "move_type": "SHOOT",   "cooldown": 5}
  ],
  "items": [
    {
      "id": 1,
      "item_type": "bone",
      "name": "骨",
      "description": "犬の本能を刺激する骨。IQの低い選手や特定犬種が引き寄せられる。",
      "image_file": "item_bone.png",
      "attracted_breeds": ["golden", "saint_bernard", "dachshund"],
      "iq_threshold": 72,
      "composure_threshold": 65,
      "base_reaction_chance": 0.35,
      "breed_bonus_chance": 0.45,
      "position_pull": 0.45,
      "composure_debuff": -12,
      "duration_minutes": 15,
      "max_uses_per_match": 2
    },
    {
      "id": 2,
      "item_type": "meat",
      "name": "肉",
      "description": "肉食系犬種が我を忘れて近づく。ブルドッグやビーグルに要注意。",
      "image_file": "item_meat.png",
      "attracted_breeds": ["bulldog", "beagle", "husky"],
      "iq_threshold": 75,
      "composure_threshold": 68,
      "base_reaction_chance": 0.40,
      "breed_bonus_chance": 0.50,
      "position_pull": 0.50,
      "speed_debuff": -8,
      "composure_debuff": -15,
      "defending_debuff": -10,
      "duration_minutes": 12,
      "max_uses_per_match": 2
    },
    {
      "id": 3,
      "item_type": "ball",
      "name": "おもちゃのボール",
      "description": "若い選手が遊びたくなる。24歳以下の選手に特に効果的。",
      "image_file": "item_ball.png",
      "attracted_breeds": ["border_collie", "golden", "dachshund"],
      "iq_threshold": 68,
      "composure_threshold": 60,
      "base_reaction_chance": 0.25,
      "breed_bonus_chance": 0.35,
      "position_pull": 0.35,
      "composure_debuff": -8,
      "duration_minutes": 10,
      "max_uses_per_match": 3
    }
  ]
}
